trustpoint_client/__init__.py
trustpoint_client/__main__.py
trustpoint_client/api/__init__.py
trustpoint_client/api/credentials.py
trustpoint_client/api/decorator.py
trustpoint_client/api/domains.py
trustpoint_client/api/exceptions.py
trustpoint_client/api/export.py
trustpoint_client/api/mdns.py
trustpoint_client/api/oid.py
trustpoint_client/api/onboard.py
trustpoint_client/api/schema.py
trustpoint_client/api/zero_touch_aoki.py
trustpoint_client/cli/__init__.py
trustpoint_client/cli/config.py
trustpoint_client/cli/credentials.py
trustpoint_client/cli/domains.py
trustpoint_client/cli/onboard.py
trustpoint_client/cli/purge.py
trustpoint_client/cli/version.py
trustpoint_client/demo_data/idevid_cert.pem
trustpoint_client/demo_data/idevid_private.key
trustpoint_client/demo_data/owner_cert_chain.pem
trustpoint_client/demo_data/rsa2048-chain.pem
trustpoint_client/demo_data/rsa2048-ee-cert.pem
trustpoint_client/enums.py
trustpoint_client-0.1.0.dist-info/AUTHORS.md
trustpoint_client-0.1.0.dist-info/LICENSE
trustpoint_client-0.1.0.dist-info/METADATA
trustpoint_client-0.1.0.dist-info/WHEEL
trustpoint_client-0.1.0.dist-info/entry_points.txt
trustpoint_client-0.1.0.dist-info/RECORD
