Metadata-Version: 2.1
Name: trustpoint-client
Version: 0.1.0
Summary: Trustpoint Client Software
Author: TrustPoint-Project
Requires-Python: >=3.10,<4.0
Classifier: Programming Language :: Python :: 3
Classifier: Programming Language :: Python :: 3.10
Classifier: Programming Language :: Python :: 3.11
Classifier: Programming Language :: Python :: 3.12
Classifier: Programming Language :: Python :: 3.13
Requires-Dist: click (>=8.1.7,<9.0.0)
Requires-Dist: cryptography (>=43.0.3,<44.0.0)
Requires-Dist: platformdirs (>=4.3.6,<5.0.0)
Requires-Dist: prettytable (>=3.12.0,<4.0.0)
Requires-Dist: pydantic (>=2.9.2,<3.0.0)
Requires-Dist: requests (>=2.32.3,<3.0.0)
Requires-Dist: trustpoint-devid-module (>=0.0.7,<0.0.8)
Requires-Dist: zeroconf (>=0.136.0,<0.137.0)
